llms_txt_action/__init__.py
llms_txt_action/entrypoint.py
llms_txt_action/utils.py
llms_txt_action-1.0.2.dist-info/METADATA
llms_txt_action-1.0.2.dist-info/WHEEL
llms_txt_action-1.0.2.dist-info/entry_points.txt
llms_txt_action-1.0.2.dist-info/licenses/LICENSE
llms_txt_action-1.0.2.dist-info/RECORD
