Metadata-Version: 2.4
Name: llms-txt-action
Version: 1.0.2
Summary: GitHub Action to make documentation more accessible to LLMs.
Project-URL: Homepage, https://github.com/demodrive-ai/llms-txt-action
Project-URL: Repository, https://github.com/demodrive-ai/llms-txt-action
Author-email: DemoDrive AI <founders@demodrive.tech>
License: MIT
License-File: LICENSE
Keywords: documentation,github-action,llm
Classifier: Development Status :: 3 - Alpha
Classifier: Intended Audience :: Developers
Classifier: Operating System :: OS Independent
Classifier: Programming Language :: Python :: 3
Classifier: Programming Language :: Python :: 3.9
Classifier: Programming Language :: Python :: 3.10
Classifier: Programming Language :: Python :: 3.11
Classifier: Programming Language :: Python :: 3.12
Classifier: Topic :: Software Development :: Documentation
Requires-Python: >=3.9
Requires-Dist: defusedxml>=0.7.1
Requires-Dist: docling>=2.14.0
Requires-Dist: firecrawl-py>=1.6.8
Requires-Dist: litellm>=1.56.8
Requires-Dist: requests>=2.31.0
Requires-Dist: rich>=13.9.4
Provides-Extra: dev
Requires-Dist: bandit>=1.7.8; extra == 'dev'
Requires-Dist: pre-commit>=3.6.0; extra == 'dev'
Requires-Dist: pytest-cov>=4.1.0; extra == 'dev'
Requires-Dist: pytest>=7.4.0; extra == 'dev'
Requires-Dist: ruff>=0.8.4; extra == 'dev'
Requires-Dist: safety>=3.0.1; extra == 'dev'
